nitransforms/__init__.py
nitransforms/_version.py
nitransforms/base.py
nitransforms/cli.py
nitransforms/conftest.py
nitransforms/linear.py
nitransforms/manip.py
nitransforms/nonlinear.py
nitransforms/patched.py
nitransforms/resampling.py
nitransforms/surface.py
nitransforms/interp/__init__.py
nitransforms/interp/bspline.py
nitransforms/io/__init__.py
nitransforms/io/afni.py
nitransforms/io/base.py
nitransforms/io/fsl.py
nitransforms/io/itk.py
nitransforms/io/lta.py
nitransforms/io/x5.py
nitransforms/tests/__init__.py
nitransforms/tests/test_base.py
nitransforms/tests/test_cli.py
nitransforms/tests/test_conversions.py
nitransforms/tests/test_io.py
nitransforms/tests/test_io_itk.py
nitransforms/tests/test_linear.py
nitransforms/tests/test_manip.py
nitransforms/tests/test_nonlinear.py
nitransforms/tests/test_resampling.py
nitransforms/tests/test_surface.py
nitransforms/tests/test_version.py
nitransforms/tests/test_x5.py
nitransforms/tests/utils.py
nitransforms/tests/data/affine-LAS.afni
nitransforms/tests/data/affine-LAS.afni-array
nitransforms/tests/data/affine-LAS.fs.lta
nitransforms/tests/data/affine-LAS.fsl
nitransforms/tests/data/affine-LAS.itk.tfm
nitransforms/tests/data/affine-LPS.afni
nitransforms/tests/data/affine-LPS.afni-array
nitransforms/tests/data/affine-LPS.fs.lta
nitransforms/tests/data/affine-LPS.fsl
nitransforms/tests/data/affine-LPS.itk.tfm
nitransforms/tests/data/affine-RAS.afni
nitransforms/tests/data/affine-RAS.afni-array
nitransforms/tests/data/affine-RAS.fs.lta
nitransforms/tests/data/affine-RAS.fs.v2v.lta
nitransforms/tests/data/affine-RAS.fsl
nitransforms/tests/data/affine-RAS.itk.tfm
nitransforms/tests/data/affine-antsComposite.h5
nitransforms/tests/data/affine-oblique.afni
nitransforms/tests/data/affine-oblique.afni-array
nitransforms/tests/data/affine-oblique.fs.lta
nitransforms/tests/data/affine-oblique.fsl
nitransforms/tests/data/affine-oblique.itk.tfm
nitransforms/tests/data/bold-to-t1w.lta
nitransforms/tests/data/bold-to-t1w.v2v.lta
nitransforms-25.1.0.dist-info/licenses/LICENSE
nitransforms-25.1.0.dist-info/METADATA
nitransforms-25.1.0.dist-info/WHEEL
nitransforms-25.1.0.dist-info/entry_points.txt
nitransforms-25.1.0.dist-info/top_level.txt
nitransforms-25.1.0.dist-info/RECORD
