Metadata-Version: 2.4
Name: nitransforms
Version: 25.1.0
Summary: NiTransforms -- Neuroimaging spatial transforms in Python.
Author-email: The NiPy developers <nipreps@gmail.com>
License: MIT License
Project-URL: Homepage, https://github.com/nipy/nitransforms
Project-URL: Manuscript, https://doi.org/10.31219/osf.io/8aq7b
Project-URL: NiBabel, https://github.com/nipy/nibabel/pull/656
Classifier: Development Status :: 2 - Pre-Alpha
Classifier: Intended Audience :: Science/Research
Classifier: Topic :: Scientific/Engineering :: Image Recognition
Classifier: License :: OSI Approved :: BSD License
Classifier: Programming Language :: Python :: 3.10
Classifier: Programming Language :: Python :: 3.11
Classifier: Programming Language :: Python :: 3.12
Classifier: Programming Language :: Python :: 3.13
Requires-Python: >=3.10
License-File: LICENSE
Requires-Dist: numpy>=2.0
Requires-Dist: scipy>=1.10
Requires-Dist: nibabel>=5.1.1
Requires-Dist: h5py>=3.11
Provides-Extra: niftiext
Requires-Dist: lxml>=4.6.4; extra == "niftiext"
Provides-Extra: test
Requires-Dist: pytest>=6.2.5; extra == "test"
Requires-Dist: pytest-cov>=2.11; extra == "test"
Requires-Dist: pytest-env; extra == "test"
Requires-Dist: pytest-xdist>=2.5; extra == "test"
Requires-Dist: coverage[toml]>=5.2.1; extra == "test"
Requires-Dist: nitransforms[niftiext]; extra == "test"
Provides-Extra: niftiexts
Requires-Dist: nitransforms[niftiext]; extra == "niftiexts"
Provides-Extra: tests
Requires-Dist: nitransforms[test]; extra == "tests"
Provides-Extra: all
Requires-Dist: nitransforms[test]; extra == "all"
Dynamic: license-file
